sqlmodelservice/__init__.py
sqlmodelservice/errors.py
sqlmodelservice/py.typed
sqlmodelservice/service.py
sqlmodelservice/utils.py
sqlmodelservice-0.5.0.dist-info/LICENSE
sqlmodelservice-0.5.0.dist-info/METADATA
sqlmodelservice-0.5.0.dist-info/WHEEL
sqlmodelservice-0.5.0.dist-info/RECORD
