Metadata-Version: 2.1
Name: sqlmodelservice
Version: 0.5.0
Summary: A generic service layer on top of SQLModel for conveniently creating APIs with frameworks like FastAPI.
Author: Peter Volf
Author-email: do.volfp@gmail.com
Requires-Python: >=3.10,<4.0
Classifier: Programming Language :: Python :: 3
Classifier: Programming Language :: Python :: 3.10
Classifier: Programming Language :: Python :: 3.11
Classifier: Programming Language :: Python :: 3.12
Requires-Dist: sqlmodel (>=0.0.14,<0.1)
